ylog.py
y_log-0.1.0.dist-info/METADATA
y_log-0.1.0.dist-info/WHEEL
y_log-0.1.0.dist-info/top_level.txt
y_log-0.1.0.dist-info/RECORD
