Metadata-Version: 2.4
Name: y-log
Version: 0.1.0
Requires-Python: >=3.12
Requires-Dist: loguru>=0.7.3
